FSDP_QLORA_IMJONEZZ/__init__.py
FSDP_QLORA_IMJONEZZ/dataloading.py
FSDP_QLORA_IMJONEZZ/logging.py
FSDP_QLORA_IMJONEZZ/model.py
FSDP_QLORA_IMJONEZZ/train.py
FSDP_QLORA_IMJONEZZ/utils.py
fsdp_qlora-0.0.1.dist-info/LICENSE
fsdp_qlora-0.0.1.dist-info/METADATA
fsdp_qlora-0.0.1.dist-info/WHEEL
fsdp_qlora-0.0.1.dist-info/top_level.txt
fsdp_qlora-0.0.1.dist-info/RECORD
